{
  "title": [
    "Republic of Estonia  (Eesti Vabariik (Estonian))"
  ],
  "Capital and largest city": [
    "Tallinn"
  ],
    "Ethnic groups (2018)": [
    "68.7% Estonians ",
    "24.9% Russians ",
    "1.8% Ukrainians ",
    "0.9% Belarusians ",
    "0.6% Finns ",
    "3.1% Others"
  ],
  "Official languages": [
    "Estonian"
  ],
  "Demonym(s)": [
    "Estonian"
  ],
  "Government": [
    "Unitary parliamentary republic"
  ],
  "President ": [
    "Kersti Kaljulaid"
  ],
  "Prime Minister ": [
    "Juri Ratas"
  ],
  "Legislature": [
    "Riigikogu"
  ]
}